thumb_gen_x/__init__.py
thumb_gen_x/__main__.py
thumb_gen_x/application.py
thumb_gen_x/config.py
thumb_gen_x/gui.py
thumb_gen_x/utils.py
thumb_gen_x/version.py
thumb_gen_x/worker.py
thumb_gen_x/fonts/RobotoCondensed-Regular.ttf
thumb_gen_x-0.0.2.dist-info/LICENSE
thumb_gen_x-0.0.2.dist-info/METADATA
thumb_gen_x-0.0.2.dist-info/WHEEL
thumb_gen_x-0.0.2.dist-info/entry_points.txt
thumb_gen_x-0.0.2.dist-info/top_level.txt
thumb_gen_x-0.0.2.dist-info/RECORD
