Metadata-Version: 2.1
Name: thumb-gen-x
Version: 0.0.2
Summary: Python application that can be used to generate video thumbnail for mp4 and mkv file types.
Home-page: https://github.com/truethari/thumb-gen-x
Author: tharindu.dev
Author-email: tharindu.nm@yahoo.com
License: MIT
Project-URL: Bug Tracker, https://github.com/truethari/thumb-gen-x/issues
Keywords: thumbnails video screenshot
Platform: UNKNOWN
Classifier: Programming Language :: Python :: 3
Classifier: License :: OSI Approved :: MIT License
Requires-Dist: Pillow
Requires-Dist: infomedia
Requires-Dist: opencv-python
Requires-Dist: tk
